{"9":[3,22,3,70],"17":[3,22,3,70],"25":[3,17,3,72],"33":[4,17,4,24],"41":[4,17,4,26],"49":[4,17,4,27],"57":[2,9,5,10],"65":[2,9,5,10],"73":[6,9,6,18],"81":[6,9,6,20],"89":[6,9,6,21],"97":[1,2,7,2],"105":[1,2,7,2],"113":[2,9,5,10],"121":[1,2,7,2],"129":[1,2,7,2],"137":[1,1,7,5],"145":[1,1,7,5],"153":[1,1,7,5],"161":[2,9,5,10],"169":[2,9,5,10],"177":[1,2,7,2],"185":[1,2,7,2],"193":[1,1,7,5],"201":[1,1,7,5],"nBranches":0,"originalCodeFileName":"/Users/madhurimachakraborty/Documents/jalangi2/experiments/trex/ft_evaltest5.js","instrumentedCodeFileName":"/Users/madhurimachakraborty/Documents/jalangi2/experiments/trex/ft_evaltest5_jalangi_.js","code":"(function(){\n        function isChecked() {\n                eval(\"var evalFun = function(){ return \\\"evalFun\\\"} \");\n                evalFun();\n        }\n        isChecked();\n})()"}