{"9":[4,25,4,32],"17":[4,37,4,60],"25":[4,25,4,61],"27":[4,25,4,36],"33":[4,25,4,62],"41":[3,24,5,18],"49":[3,24,5,18],"57":[3,24,5,18],"65":[8,25,8,32],"73":[8,37,8,61],"81":[8,25,8,62],"83":[8,25,8,36],"89":[8,25,8,63],"97":[7,24,9,18],"105":[7,24,9,18],"113":[7,24,9,18],"121":[12,25,12,32],"129":[12,37,12,60],"137":[12,25,12,61],"139":[12,25,12,36],"145":[12,25,12,62],"153":[11,24,13,18],"161":[11,24,13,18],"169":[11,24,13,18],"177":[14,24,14,30],"185":[2,31,15,10],"193":[2,31,15,10],"201":[2,31,15,10],"209":[17,17,17,26],"217":[17,27,17,28],"225":[17,17,17,31],"227":[17,17,17,29],"233":[17,17,17,31],"241":[16,9,20,10],"249":[16,9,20,10],"257":[21,9,21,12],"265":[21,13,21,28],"273":[21,29,21,35],"281":[21,13,21,36],"289":[21,9,21,37],"297":[21,9,21,37],"305":[1,2,22,10],"313":[1,2,22,10],"321":[1,2,22,10],"329":[16,9,20,10],"337":[1,2,22,10],"345":[1,2,22,10],"353":[1,1,22,13],"361":[1,1,22,13],"369":[1,1,22,13],"377":[3,24,5,18],"385":[3,24,5,18],"393":[7,24,9,18],"401":[7,24,9,18],"409":[11,24,13,18],"417":[11,24,13,18],"425":[16,9,20,10],"433":[16,9,20,10],"441":[1,2,22,10],"449":[1,2,22,10],"457":[1,1,22,13],"465":[1,1,22,13],"nBranches":0,"originalCodeFileName":"/Users/madhurimachakraborty/Documents/jalangi2/experiments/trex/ft_strngargs.js","instrumentedCodeFileName":"/Users/madhurimachakraborty/Documents/jalangi2/experiments/trex/ft_strngargs_jalangi_.js","code":"(function(){\n        var arrayOfFunction = {\n                \"fun1\":function() { \n                        console.log(\"Inside First function\"); \n                }, \n                \n                \"fun2\":function() { \n                        console.log(\"Inside Second function\"); \n                }, \n                \n                \"fun3\":function() { \n                        console.log(\"Inside Third function\"); \n                },\n                \"fun4\":\"fun3\"\n        }\n        function foo(){\n                arguments[0]()\n                //x()\n                \n        }\n        foo(arrayOfFunction[\"fun1\"])\n        })()"}